MANIFEST.in
setup.py
src/spp.c
src/spp.pyx
src/c/hbuf.c
src/c/hbuf.h
src/c/spp.c
src/c/spp.h