Metadata-Version: 1.0
Name: spp
Version: 0.0.3
Summary: My Simple Protocol Parser For Python, Built For Speed
Home-page: https://github.com/hit9/spp_py
Author: hit9
Author-email: hit9@icloud.com
License: MIT
Platform: UNKNOWN
